MANIFEST.in
setup.cfg
setup.py
caravel/__init__.py
caravel/ascii_art.py
caravel/config.py
caravel/dataframe.py
caravel/extract_table_names.py
caravel/forms.py
caravel/models.py
caravel/source_registry.py
caravel/sql_lab.py
caravel/utils.py
caravel/views.py
caravel/viz.py
caravel/bin/__init__.py
caravel/bin/caravel
caravel/data/__init__.py
caravel/data/__init__.pyc
caravel/data/birth_names.csv.gz
caravel/data/birth_names.json.gz
caravel/data/countries.json.gz
caravel/data/countries.md
caravel/data/countries.py
caravel/data/countries.pyc
caravel/data/energy.json.gz
caravel/data/multiformat_time_series.json.gz
caravel/data/random_time_series.json.gz
caravel/data/san_francisco.csv.gz
caravel/data/unicode_utf8_unixnl_test.csv
caravel/migrations/README
caravel/migrations/__init__.py
caravel/migrations/alembic.ini
caravel/migrations/env.py
caravel/migrations/script.py.mako
caravel/migrations/versions/1226819ee0e3_fix_wrong_constraint_on_table_columns.py
caravel/migrations/versions/12d55656cbca_is_featured.py
caravel/migrations/versions/18e88e1cc004_making_audit_nullable.py
caravel/migrations/versions/1a48a5411020_adding_slug_to_dash.py
caravel/migrations/versions/1d2ddd543133_log_dt.py
caravel/migrations/versions/1e2841a4128_.py
caravel/migrations/versions/2591d77e9831_user_id.py
caravel/migrations/versions/27ae655e4247_make_creator_owners.py
caravel/migrations/versions/289ce07647b_add_encrypted_password_field.py
caravel/migrations/versions/2929af7925ed_tz_offsets_in_data_sources.py
caravel/migrations/versions/315b3f4da9b0_adding_log_model.py
caravel/migrations/versions/33d996bcc382_update_slice_model.py
caravel/migrations/versions/3b626e2a6783_sync_db_with_models.py
caravel/migrations/versions/3c3ffe173e4f_add_sql_string_to_table.py
caravel/migrations/versions/41f6a59a61f2_database_options_for_sql_lab.py
caravel/migrations/versions/430039611635_log_more.py
caravel/migrations/versions/43df8de3a5f4_dash_json.py
creavel.egg-info/PKG-INFO
creavel.egg-info/SOURCES.txt
creavel.egg-info/dependency_links.txt
creavel.egg-info/not-zip-safe
creavel.egg-info/requires.txt
creavel.egg-info/top_level.txt