Metadata-Version: 1.1
Name: creavel
Version: 0.11.0
Summary: A interactive data visualization platform build on SqlAlchemy and druid.io
Home-page: https://github.com/airbnb/caravel
Author: Maxime Beauchemin
Author-email: maximebeauchemin@gmail.com
License: UNKNOWN
Download-URL: https://git.creditx.com/liudong/creavel
Platform: UNKNOWN
Classifier: Programming Language :: Python :: 2.7
Classifier: Programming Language :: Python :: 3.4
Classifier: Programming Language :: Python :: 3.5
